kaiju_files/__init__.py
kaiju_files/services.py
kaiju_files/types.py
kaiju_files/tests/__init__.py
kaiju_files/tests/fixtures.py
kaiju_files/tests/test_services.py
kaiju_files-2.1.2.dist-info/LICENSE
kaiju_files-2.1.2.dist-info/METADATA
kaiju_files-2.1.2.dist-info/WHEEL
kaiju_files-2.1.2.dist-info/top_level.txt
kaiju_files-2.1.2.dist-info/RECORD
